google_datacatalog_sisense_connector-0.1.0-py3.6-nspkg.pth
google/datacatalog_connectors/sisense/__init__.py
google/datacatalog_connectors/sisense/sisense2datacatalog_cli.py
google/datacatalog_connectors/sisense/addons/__init__.py
google/datacatalog_connectors/sisense/addons/elasticube_dependency_finder.py
google/datacatalog_connectors/sisense/addons/elasticube_dependency_printer.py
google/datacatalog_connectors/sisense/addons/linked_resource_based_finder.py
google/datacatalog_connectors/sisense/addons/tag_based_finder.py
google/datacatalog_connectors/sisense/prepare/__init__.py
google/datacatalog_connectors/sisense/prepare/assembled_entry_factory.py
google/datacatalog_connectors/sisense/prepare/constants.py
google/datacatalog_connectors/sisense/prepare/datacatalog_entry_factory.py
google/datacatalog_connectors/sisense/prepare/datacatalog_tag_factory.py
google/datacatalog_connectors/sisense/prepare/datacatalog_tag_template_factory.py
google/datacatalog_connectors/sisense/prepare/entry_relationship_mapper.py
google/datacatalog_connectors/sisense/prepare/sisense_connector_strings_helper.py
google/datacatalog_connectors/sisense/scrape/__init__.py
google/datacatalog_connectors/sisense/scrape/authenticator.py
google/datacatalog_connectors/sisense/scrape/constants.py
google/datacatalog_connectors/sisense/scrape/metadata_scraper.py
google/datacatalog_connectors/sisense/scrape/rest_api_helper.py
google/datacatalog_connectors/sisense/sync/__init__.py
google/datacatalog_connectors/sisense/sync/metadata_synchronizer.py
google_datacatalog_sisense_connector-0.1.0.dist-info/METADATA
google_datacatalog_sisense_connector-0.1.0.dist-info/WHEEL
google_datacatalog_sisense_connector-0.1.0.dist-info/entry_points.txt
google_datacatalog_sisense_connector-0.1.0.dist-info/namespace_packages.txt
google_datacatalog_sisense_connector-0.1.0.dist-info/top_level.txt
google_datacatalog_sisense_connector-0.1.0.dist-info/RECORD
