Metadata-Version: 2.1
Name: google-datacatalog-sisense-connector
Version: 0.1.0
Summary: Package for ingesting Sisense metadata into Google Cloud Data Catalog
Home-page: UNKNOWN
Author: Google LLC
License: UNKNOWN
Platform: Posix; MacOS X; Windows
Classifier: Development Status :: 4 - Beta
Classifier: Natural Language :: English
Classifier: Programming Language :: Python
Classifier: Programming Language :: Python :: 3.6
Classifier: Programming Language :: Python :: 3.7
Classifier: Programming Language :: Python :: 3.8
Requires-Dist: google-datacatalog-connectors-commons (~=0.6.9)
Requires-Dist: tabulate (~=0.8.9)
